main.py
android_mobile_mcp-2.4.1.dist-info/METADATA
android_mobile_mcp-2.4.1.dist-info/WHEEL
android_mobile_mcp-2.4.1.dist-info/entry_points.txt
android_mobile_mcp-2.4.1.dist-info/top_level.txt
android_mobile_mcp-2.4.1.dist-info/RECORD
