Metadata-Version: 2.4
Name: android-mobile-mcp
Version: 2.4.1
Summary: Android Mobile MCP
Author-email: erichung0906 <rthung96@gmail.com>
Project-URL: Bug Tracker, https://github.com/erichung9060/Android-Mobile-MCP/issues
Project-URL: Repository, https://github.com/erichung9060/Android-Mobile-MCP
Keywords: android,mobile,mcp,mobile-mcp,android-mcp
Requires-Dist: uiautomator2
Requires-Dist: fastmcp
